plantsim/__init__.py
plantsim/attribute_explorer.py
plantsim/error_code.py
plantsim/pandas_table.py
plantsim/plantsim.py
plantsim/table.py
plantsim-0.0.3.dist-info/LICENSE
plantsim-0.0.3.dist-info/METADATA
plantsim-0.0.3.dist-info/WHEEL
plantsim-0.0.3.dist-info/top_level.txt
plantsim-0.0.3.dist-info/RECORD
