Metadata-Version: 2.1
Name: plantsim
Version: 0.0.3
Summary: Python wrapper for Plant Simulation
Home-page: UNKNOWN
Author: Tilo van Ekeris
Author-email: tilo@vanekeris.de
License: UNKNOWN
Platform: UNKNOWN
Classifier: Programming Language :: Python :: 3
Classifier: Operating System :: Microsoft :: Windows
Requires-Python: >=3.8
License-File: LICENSE
Requires-Dist: pywin32 (==225)
Requires-Dist: texttable
Requires-Dist: pandas
